ai_lsp/__init__.py
ai_lsp/main.py
ai_lsp-0.1.0.dist-info/METADATA
ai_lsp-0.1.0.dist-info/WHEEL
ai_lsp-0.1.0.dist-info/entry_points.txt
ai_lsp-0.1.0.dist-info/RECORD
