Metadata-Version: 2.4
Name: ai-lsp
Version: 0.1.0
Summary: AI-powered Language Server with intelligent diagnostics
Project-URL: Homepage, https://github.com/benomahony/ai-lsp
Project-URL: Repository, https://github.com/benomahony/ai-lsp
Author-email: benomahony <ben.omahony@thoughtworks.com>
License-Expression: MIT
Requires-Python: >=3.12
Requires-Dist: pydantic-ai>=0.4.11
Requires-Dist: pydantic-settings>=2.10.1
Requires-Dist: pydantic>=2.0.0
Requires-Dist: pygls>=1.3.0
Requires-Dist: ruff>=0.12.12
Requires-Dist: typer>=0.12.0
